onecontext/__about__.py
onecontext/__init__.py
onecontext/client.py
onecontext/context.py
onecontext/main.py
onecontext/models.py
onecontext/scrathc.py
onecontext/utils.py
onecontext-3.3.13.dist-info/METADATA
onecontext-3.3.13.dist-info/WHEEL
onecontext-3.3.13.dist-info/licenses/LICENSE.txt
onecontext-3.3.13.dist-info/RECORD
