Metadata-Version: 2.3
Name: onecontext
Version: 3.3.13
Project-URL: Documentation, https://github.com/onecontext/onecontext-python#readme
Project-URL: Issues, https://github.com/onecontext/onecontext-python/issues
Project-URL: Source, https://github.com/onecontext/onecontext-python
Author-email: Serge Mosesov <smosesov@gmail.com>, Ross Murphy <ross.a.murphy@gmail.com>
License: MIT
Classifier: Development Status :: 4 - Beta
Classifier: Programming Language :: Python
Classifier: Programming Language :: Python :: 3.7
Classifier: Programming Language :: Python :: 3.8
Classifier: Programming Language :: Python :: 3.9
Classifier: Programming Language :: Python :: 3.10
Classifier: Programming Language :: Python :: 3.11
Classifier: Programming Language :: Python :: Implementation :: CPython
Classifier: Programming Language :: Python :: Implementation :: PyPy
Requires-Python: >=3.7
Requires-Dist: requests
Requires-Dist: tqdm
